stringsmith/__init__.py
stringsmith/core.py
stringsmith-0.1.1.dist-info/METADATA
stringsmith-0.1.1.dist-info/WHEEL
stringsmith-0.1.1.dist-info/entry_points.txt
stringsmith-0.1.1.dist-info/top_level.txt
stringsmith-0.1.1.dist-info/RECORD
