Metadata-Version: 2.4
Name: stringsmith
Version: 0.1.1
Summary: A lightweight toolkit for generating random strings: numbers, alphabets, alphanumeric with symbols.
Author: Aman Jain
License: MIT
Requires-Python: >=3.7
